sqlalchemy2atlas/__init__.py
sqlalchemy2atlas/containers.py
sqlalchemy2atlas/exceptions.py
sqlalchemy2atlas/sqlalchemy2atlas.py
sqlalchemy2atlas-0.1.9.dist-info/entry_points.txt
sqlalchemy2atlas-0.1.9.dist-info/LICENSE
sqlalchemy2atlas-0.1.9.dist-info/WHEEL
sqlalchemy2atlas-0.1.9.dist-info/METADATA
sqlalchemy2atlas-0.1.9.dist-info/RECORD
