Metadata-Version: 2.1
Name: sqlalchemy2atlas
Version: 0.1.9
Summary: Converts SQLALchemy Base Classes to AtlasGo HCL.
License: MIT
Author: Fraser Isbester
Author-email: 28307321+Fraser-Isbester@users.noreply.github.com
Requires-Python: >=3.10,<4.0
Classifier: License :: OSI Approved :: MIT License
Classifier: Programming Language :: Python :: 3
Classifier: Programming Language :: Python :: 3.10
Classifier: Programming Language :: Python :: 3.11
Requires-Dist: SQLAlchemy (>=1.4,<2.0)
Requires-Dist: docker (>=6.0,<7.0)
Requires-Dist: psycopg2 (>=2.9,<3.0)
